short_transformers/__init__.py
short_transformers/dist.py
short_transformers/model_factory/diff.txt
short_transformers/model_factory/duplicate_layer.py
short_transformers/model_factory/remove_and_duplicate.py
short_transformers/model_factory/remove_and_duplicate_with_merging.py
short_transformers/model_factory/remove_by_merging.py
short_transformers/model_factory/replace_layer_and_cut.py
short_transformers/short_transformer.py
short_transformers/utils/__init__.py
short_transformers/utils/log.py
short_transformers/utils/plot.py
short_transformers/utils/utils.py
short_transformers-1.0.0.dist-info/METADATA
short_transformers-1.0.0.dist-info/WHEEL
short_transformers-1.0.0.dist-info/RECORD
