Metadata-Version: 2.1
Name: short-transformers
Version: 1.0.0
Summary: Cutting transformers layers
License: MIT
Author: Melisa Russak
Author-email: melisa@russak.biz
Requires-Python: >=3.10,<4.0
Classifier: License :: OSI Approved :: MIT License
Classifier: Programming Language :: Python :: 3
Classifier: Programming Language :: Python :: 3.10
Classifier: Programming Language :: Python :: 3.11
Classifier: Programming Language :: Python :: 3.12
Requires-Dist: matplotlib (>=3.8.4,<4.0.0)
Requires-Dist: seaborn (>=0.13.2,<0.14.0)
Requires-Dist: tqdm (>=4.66.4,<5.0.0)
